mmcq/__init__.py
mmcq/color.py
mmcq/constant.py
mmcq/math_.py
mmcq/palette.py
mmcq/quantize.py
mmcq/region.py
mmcq/struct.py
mmcq.py-0.1.1.dist-info/LICENSE
mmcq.py-0.1.1.dist-info/METADATA
mmcq.py-0.1.1.dist-info/WHEEL
mmcq.py-0.1.1.dist-info/top_level.txt
mmcq.py-0.1.1.dist-info/RECORD
