Metadata-Version: 2.1
Name: mmcq.py
Version: 0.1.1
Summary: Python mmcq implementation
Home-page: UNKNOWN
License: MIT
Platform: UNKNOWN
Classifier: License :: OSI Approved :: MIT License
Classifier: Topic :: Utilities
Classifier: Programming Language :: Python :: 3 :: Only
Requires-Dist: Pillow
